setup.py
G_and_B_distributions_package/Binomialdistribution.py
G_and_B_distributions_package/Gaussiandistribution.py
G_and_B_distributions_package/Generaldistribution.py
G_and_B_distributions_package/__init__.py
G_and_B_distributions_package.egg-info/PKG-INFO
G_and_B_distributions_package.egg-info/SOURCES.txt
G_and_B_distributions_package.egg-info/dependency_links.txt
G_and_B_distributions_package.egg-info/not-zip-safe
G_and_B_distributions_package.egg-info/top_level.txt